regressproxy/__init__.py
regressproxy/models_cel.py
regressproxy/models_pymc3.py
regressproxy/models_pymc4.py
regressproxy-0.0.2.dist-info/LICENSE
regressproxy-0.0.2.dist-info/METADATA
regressproxy-0.0.2.dist-info/WHEEL
regressproxy-0.0.2.dist-info/top_level.txt
regressproxy-0.0.2.dist-info/RECORD
