Metadata-Version: 2.1
Name: regressproxy
Version: 0.0.2
Summary: Versatile proxy models for regression analysis
Home-page: http://github.com/st-bender/pyregressproxy
Author: Stefan Bender
Author-email: stefan.bender@ntnu.no
License: GPLv2
Classifier: Development Status :: 3 - Alpha
Classifier: Intended Audience :: Science/Research
Classifier: License :: OSI Approved :: GNU General Public License v2 (GPLv2)
Classifier: Programming Language :: Python
Classifier: Programming Language :: Python :: 2
Classifier: Programming Language :: Python :: 3
Classifier: Topic :: Scientific/Engineering :: Physics
Classifier: Topic :: Utilities
License-File: LICENSE
Requires-Dist: numpy (>=1.13.0)
Requires-Dist: celerite (>=0.3.0)
Provides-Extra: all
Requires-Dist: pymc3 (>=3.10) ; extra == 'all'
Requires-Dist: pymc (>=4) ; extra == 'all'
Requires-Dist: pytest ; extra == 'all'
Provides-Extra: pymc3
Requires-Dist: pymc3 (>=3.10) ; extra == 'pymc3'
Provides-Extra: pymc4
Requires-Dist: pymc (>=4) ; extra == 'pymc4'
Provides-Extra: tests
Requires-Dist: pytest ; extra == 'tests'
Provides-Extra: theano
Requires-Dist: pymc3 (>=3.10) ; extra == 'theano'
